{
  "main": {
    "id": "07063a78dd2ba8ee",
    "type": "split",
    "children": [
      {
        "id": "f327caa4fa091f54",
        "type": "tabs",
        "children": [
          {
            "id": "07084dd823b72171",
            "type": "leaf",
            "state": {
              "type": "markdown",
              "state": {
                "file": "Game_Dev/art tools and animators.md",
                "mode": "source",
                "source": true
              }
            }
          }
        ]
      }
    ],
    "direction": "vertical"
  },
  "left": {
    "id": "a60c00ad5cbf3654",
    "type": "split",
    "children": [
      {
        "id": "07cb50cb5e0cf2ab",
        "type": "tabs",
        "children": [
          {
            "id": "6ff3333e5d0c9ffe",
            "type": "leaf",
            "state": {
              "type": "file-explorer",
              "state": {
                "sortOrder": "alphabetical"
              }
            }
          },
          {
            "id": "600d75c6a2887bcd",
            "type": "leaf",
            "state": {
              "type": "search",
              "state": {
                "query": "",
                "matchingCase": false,
                "explainSearch": false,
                "collapseAll": false,
                "extraContext": false,
                "sortOrder": "alphabetical"
              }
            }
          }
        ]
      }
    ],
    "direction": "horizontal",
    "width": 352.5
  },
  "right": {
    "id": "42e477e31d1edcfd",
    "type": "split",
    "children": [
      {
        "id": "4dd50f48c8bde251",
        "type": "tabs",
        "children": [
          {
            "id": "544ad3de8d3f79ab",
            "type": "leaf",
            "state": {
              "type": "backlink",
              "state": {
                "file": "Game_Dev/art tools and animators.md",
                "collapseAll": false,
                "extraContext": false,
                "sortOrder": "alphabetical",
                "showSearch": false,
                "searchQuery": "",
                "backlinkCollapsed": false,
                "unlinkedCollapsed": true
              }
            }
          },
          {
            "id": "0c1cf9e1a3c3b6ca",
            "type": "leaf",
            "state": {
              "type": "outline",
              "state": {
                "file": "Game_Dev/art tools and animators.md"
              }
            }
          },
          {
            "id": "5009ead0359b56ff",
            "type": "leaf",
            "state": {
              "type": "side-panel-control-view",
              "state": {}
            }
          }
        ],
        "currentTab": 2
      }
    ],
    "direction": "horizontal",
    "width": 300,
    "collapsed": true
  },
  "left-ribbon": {
    "hiddenItems": {
      "switcher:Open quick switcher": false,
      "graph:Open graph view": false,
      "canvas:Create new canvas": false,
      "command-palette:Open command palette": false,
      "markdown-importer:Open format converter": false,
      "obsidian-markdown-formatting-assistant-plugin:Open Markdown Formatting Assistant": false
    }
  },
  "active": "07084dd823b72171",
  "lastOpenFiles": [
    "Game_Dev/Game_Dev.md",
    "swift_keywords/Public.md",
    "images/how the table view work.jpg",
    "Xcode/Debugging/Debugging.md",
    "Xcode/Debugging/Breakpoints in Xcode.md",
    "Xcode/Debugging",
    "Xcode",
    "UIkit/UITableView.md",
    "Swift/typecasting.md",
    "Swift/optional binding with if let.md",
    "Swift/ViewControllers/Tableview - swift.md",
    "Swift/ViewControllers",
    "Swift/Force Unwrapping.md",
    "ObjC/TableView - ObjC.md",
    "ObjC/ObjC Keywords/Objc - Keywords.md",
    "ObjC/ObjC Keywords",
    "ObjC/DAO - Data access object.md",
    "Game_Dev/animation in SpriteKit.md",
    "Game_Dev/Skaction Class.md",
    "Game_Dev/art tools and animators.md",
    "Clean Code/Design patterns/Factory Method.md",
    "Clean Code/Design patterns/Design Patterns.md",
    "Clean Code/Design patterns/Adapter pattern.md",
    "Clean Code/Design patterns",
    "Clean Code/Design Principles.md",
    "Clean Code/Coding Standrads.md",
    "Clean Code/Clean Code.md",
    "Clean Code/Becoming a exceptional programmer.md",
    "Clean Code",
    "typecasting.md",
    "optional binding with if let.md",
    "animation in SpriteKit.md",
    "UIkit/Tableview.md",
    "Debugging",
    "images/how the table view work.JPG",
    "images/collections swift.png",
    "images/uikit_classes.jpg",
    "images/live_preview.png",
    "Untitled 1.canvas",
    "Untitled.canvas",
    "iOS dev",
    "ObjC/iOS dev"
  ]
}